cmc_api/__init__.py
cmc_api/coinmarketcap.py
cmc_api/exceptions.py
cmc_api-0.0.1.dist-info/LICENSE.txt
cmc_api-0.0.1.dist-info/METADATA
cmc_api-0.0.1.dist-info/WHEEL
cmc_api-0.0.1.dist-info/top_level.txt
cmc_api-0.0.1.dist-info/RECORD
