Metadata-Version: 2.1
Name: cmc-api
Version: 0.0.1
Summary: Unofficial wrapper for coinmarketcap api
Home-page: https://github.com/bizzyvinci/cmc-api
Author: Bisola Olasehinde
Author-email: horlasehinde@gmail.com
License: MIT
Keywords: coinmarketcap,cmc,API,crypto,cryptocurrency
Platform: UNKNOWN
Classifier: Programming Language :: Python :: 3
Classifier: License :: OSI Approved :: MIT License
Classifier: Operating System :: OS Independent
Requires-Python: >=3
Requires-Dist: requests
